pyrest/__init__.py
pyrest/api.py
pyrest/images.py
pyrest/store.py
pyrest/variable.py
snapyrest/__init__.py
snapyrest/api.py
snapyrest/images.py
snapyrest/store.py
snapyrest/variable.py
snapyrest-0.2.0.dist-info/LICENSE
snapyrest-0.2.0.dist-info/METADATA
snapyrest-0.2.0.dist-info/WHEEL
snapyrest-0.2.0.dist-info/top_level.txt
snapyrest-0.2.0.dist-info/RECORD
