Metadata-Version: 2.1
Name: snapyrest
Version: 0.2.0
Summary: Package to test Rest API endpoints along with snap mode and image comparison functionality
Home-page: https://github.com/nareshnavinash/pyrest
Author: Naresh Sekar
Author-email: nareshnavinash@gmail.com
Keywords: REST,API,API-Automation,Image comparison through response from REST API
Classifier: Programming Language :: Python :: 3
Classifier: License :: OSI Approved :: GNU Lesser General Public License v3 (LGPLv3)
Classifier: Operating System :: OS Independent
Classifier: Topic :: Software Development :: Quality Assurance
Classifier: Topic :: Software Development :: Testing
Requires-Python: >=3.6
License-File: LICENSE
Requires-Dist: pyyaml (==6.0)
Requires-Dist: flake8 (==4.0.1)
Requires-Dist: imgcompare (==2.0.1)
Requires-Dist: diffimg (==0.3.0)
